volare/__init__.py
volare/__main__.py
volare/__version__.py
volare/build/__init__.py
volare/build/common.py
volare/build/gf180mcu.py
volare/build/git_multi_clone.py
volare/build/ihp_sg13g2.py
volare/build/sky130.py
volare/click_common.py
volare/common.py
volare/families.py
volare/github.py
volare/manage.py
volare/py.typed
volare-0.20.5.dist-info/METADATA
volare-0.20.5.dist-info/WHEEL
volare-0.20.5.dist-info/entry_points.txt
volare-0.20.5.dist-info/RECORD
